{"type":"object","properties":{"basePrice":{"type":"number","description":"Base price for the day"},"servicesPrice":{"type":"number","description":"Services price for the day"},"childrenPrice":{"type":"number","description":"Children price for the day"},"rateOptionPrice":{"type":"number","description":"Rate option price for the day"},"finalPrice":{"type":"number","description":"Final price for the day"},"status":{"type":"string","enum":["WAITING_PAYMENT","CONFIRMED","CHECKED_IN","CHECKED_OUT","ABANDONED","CANCELLED","PAYMENT_FAILED","OVERBOOKED","WAITING_LIST"],"example":"CONFIRMED"},"guestUser":{"type":"object","properties":{"email":{"type":"string","example":"user@gmail.com"},"firstName":{"type":"string","example":"user"},"lastName":{"type":"string","example":"user"},"phone":{"type":"string","example":"489831034"},"password":{"type":"string","example":"123"},"metaData":{"type":"object","example":"{preferences: {notifications: true}"}},"required":["email","firstName","password"],"x-readme-ref-name":"UserCreateDTO"},"sellerUserId":{"type":"string","example":"f47ac10b-58cc-4372-a567-0e02b2c3d479"},"saleChannel":{"type":"string","enum":["RECEPTION","PHONE","WHATSAPP","INSTAGRAM","TIKTOK","EMAIL","BOOKSUITE","OTHER"],"example":"BOOKSUITE"},"startDate":{"type":"string","example":"2025-01-14"},"endDate":{"type":"string","example":"2024-10-10"},"adults":{"type":"number","example":"2"},"ageGroups":{"type":"array","items":{"type":"object","properties":{"quantity":{"type":"number","example":2},"ageGroupId":{"type":"string","example":"f47ac10b-58cc-4372-a567-0e02b2c3d479"}},"required":["quantity","ageGroupId"],"x-readme-ref-name":"ReservationAgeGroupDTO"}},"notes":{"type":"string","example":"Featured booking"},"housingUnitId":{"type":"string","example":"f47ac10b-58cc-4372-a567-0e02b2c3d479"},"housingUnitTypeId":{"type":"string","example":"f47ac10b-58cc-4372-a567-0e02b2c3d479"},"services":{"type":"array","items":{"type":"object","properties":{"quantity":{"type":"number","example":2},"totalPrice":{"type":"number","example":150},"serviceId":{"type":"string","example":"f47ac10b-58cc-4372-a567-0e02b2c3d479"}},"required":["quantity","totalPrice","serviceId"],"x-readme-ref-name":"ReservationServiceDTO"}},"rateOptionId":{"type":"string"}},"required":["basePrice","servicesPrice","childrenPrice","rateOptionPrice","finalPrice","status","guestUser","sellerUserId","startDate","endDate","adults","ageGroups","notes","housingUnitId","housingUnitTypeId","services"],"x-readme-ref-name":"ReservationCreateDTO"}